dwys/__init__.py
dwys-0.0.4.dist-info/LICENSE
dwys-0.0.4.dist-info/WHEEL
dwys-0.0.4.dist-info/METADATA
dwys-0.0.4.dist-info/RECORD
