Metadata-Version: 2.1
Name: dwys
Version: 0.0.4
Summary: A language agnostic doctesting library
License: MIT
Author: Vince Knight
Author-email: vincent.knight@gmail.com
Requires-Python: >=3.7,<4.0
Classifier: License :: OSI Approved :: MIT License
Classifier: Programming Language :: Python :: 3
Classifier: Programming Language :: Python :: 3.7
